md_corpus/__init__.py
md_corpus/cli.py
md_corpus/exceptions.py
md_corpus/providers/__init__.py
md_corpus/providers/aliyun.py
md_corpus/providers/aws.py
md_corpus/providers/base.py
md_corpus-0.1.1.dist-info/METADATA
md_corpus-0.1.1.dist-info/WHEEL
md_corpus-0.1.1.dist-info/entry_points.txt
md_corpus-0.1.1.dist-info/licenses/LICENSE
md_corpus-0.1.1.dist-info/RECORD
