Metadata-Version: 2.4
Name: md-corpus
Version: 0.1.1
Summary: A Python package for integrating Markdown files with cloud object storage
Project-URL: Homepage, https://github.com/wangyiyang/md-corpus
Project-URL: Bug Tracker, https://github.com/wangyiyang/md-corpus/issues
Author-email: wangyiyang <wangyiyang.kk@gmail.com>
License-Expression: MIT
License-File: LICENSE
Classifier: License :: OSI Approved :: MIT License
Classifier: Operating System :: OS Independent
Classifier: Programming Language :: Python :: 3
Requires-Python: >=3.10
Requires-Dist: boto3>=1.26.0
Requires-Dist: click>=8.0.0
Requires-Dist: markdown>=3.4.0
Requires-Dist: mdformat>=0.7.17
Requires-Dist: oss2>=2.16.0
